fishauth/__init__.py
fishauth/main.py
fishauth/models/__init__.py
fishauth/models/application.py
fishauth/models/base.py
fishauth/models/genero.py
fishauth/models/organization.py
fishauth/models/organizationsuser.py
fishauth/models/permissions.py
fishauth/models/permissionsroles.py
fishauth/models/role.py
fishauth/models/sexo.py
fishauth/models/user.py
fishauth/models/userroles.py
fishauth-0.1.7.dist-info/LICENSE
fishauth-0.1.7.dist-info/METADATA
fishauth-0.1.7.dist-info/WHEEL
fishauth-0.1.7.dist-info/top_level.txt
fishauth-0.1.7.dist-info/RECORD
