Metadata-Version: 2.1
Name: fishauth
Version: 0.1.7
Summary: Libraries that have models and methods to handle user authentication
Home-page: https://github.com/jrujano/fishauth-library
Author: Johan Rujano
Author-email: johanrujano@gmail.com
License: https://www.apache.org/licenses/LICENSE-2.0
Keywords: tools authentication login auth session
Classifier: Programming Language :: Python :: 3.10
Classifier: Development Status :: 4 - Beta
Classifier: Topic :: Utilities
Classifier: Intended Audience :: Developers
Classifier: Intended Audience :: Information Technology
Classifier: Intended Audience :: System Administrators
License-File: LICENSE
